backtesting_indicators/__init__.py
backtesting_indicators/aberration.py
backtesting_indicators/above.py
backtesting_indicators/above_value.py
backtesting_indicators/accbands.py
backtesting_indicators/ad.py
backtesting_indicators/adosc.py
backtesting_indicators/adx.py
backtesting_indicators/alma.py
backtesting_indicators/amat.py
backtesting_indicators/ao.py
backtesting_indicators/aobv.py
backtesting_indicators/apo.py
backtesting_indicators/aroon.py
backtesting_indicators/atr.py
backtesting_indicators/bbands.py
backtesting_indicators/below.py
backtesting_indicators/below_value.py
backtesting_indicators/bias.py
backtesting_indicators/bop.py
backtesting_indicators/brar.py
backtesting_indicators/cci.py
backtesting_indicators/cdl_pattern.py
backtesting_indicators/cdl_z.py
backtesting_indicators/cfo.py
backtesting_indicators/cg.py
backtesting_indicators/chop.py
backtesting_indicators/cksp.py
backtesting_indicators/cmf.py
backtesting_indicators/cmo.py
backtesting_indicators/coppock.py
backtesting_indicators/cross.py
backtesting_indicators/cross_value.py
backtesting_indicators/cti.py
backtesting_indicators/decay.py
backtesting_indicators/decreasing.py
backtesting_indicators/dema.py
backtesting_indicators/dm.py
backtesting_indicators/donchian.py
backtesting_indicators/dpo.py
backtesting_indicators/ebsw.py
backtesting_indicators/efi.py
backtesting_indicators/ema.py
backtesting_indicators/entropy.py
backtesting_indicators/eom.py
backtesting_indicators/er.py
backtesting_indicators/eri.py
backtesting_indicators/fisher.py
backtesting_indicators/fwma.py
backtesting_indicators/ha.py
backtesting_indicators/hilo.py
backtesting_indicators/hl2.py
backtesting_indicators/hlc3.py
backtesting_indicators/hma.py
backtesting_indicators/hwc.py
backtesting_indicators/hwma.py
backtesting_indicators/increasing.py
backtesting_indicators/inertia.py
backtesting_indicators/jma.py
backtesting_indicators/kama.py
backtesting_indicators/kc.py
backtesting_indicators/kdj.py
backtesting_indicators/kst.py
backtesting_indicators-0.0.1.dist-info/METADATA
backtesting_indicators-0.0.1.dist-info/WHEEL
backtesting_indicators-0.0.1.dist-info/top_level.txt
backtesting_indicators-0.0.1.dist-info/RECORD
